flaxer/__init__.py
flaxer/flaxer.py
flaxer-0.0.12.dist-info/METADATA
flaxer-0.0.12.dist-info/WHEEL
flaxer-0.0.12.dist-info/entry_points.txt
flaxer-0.0.12.dist-info/top_level.txt
flaxer-0.0.12.dist-info/RECORD
