Metadata-Version: 2.1
Name: flaxer
Version: 0.0.12
Summary: Like flake8, but a fixer
Home-page: https://github.com/yangyangxcf/flaxer
Author: yana
Author-email: yana021022@example.com
License: UNKNOWN
Platform: UNKNOWN
Classifier: Programming Language :: Python :: 3
Classifier: License :: OSI Approved :: MIT License
Classifier: Operating System :: OS Independent
Requires-Python: >=3.6
Requires-Dist: click
Requires-Dist: yapf
